destructipy/__init__.py
destructipy/__main__.py
destructipy-0.0.5.dist-info/LICENSE
destructipy-0.0.5.dist-info/METADATA
destructipy-0.0.5.dist-info/WHEEL
destructipy-0.0.5.dist-info/top_level.txt
destructipy-0.0.5.dist-info/RECORD
