Metadata-Version: 2.1
Name: destructipy
Version: 0.0.5
Summary: es6 style dict/object destructure for python
Home-page: https://github.com/marxus/destructipy
Author: Amit Marcus
Author-email: marxus@gmail.com
License: UNKNOWN
Platform: UNKNOWN
